pifcap/__init__.py
pifcap/autoexposure.py
pifcap/camera.py
pifcap/pifcap.py
pifcap/pifcap2fits.py
pifcap/pifcap_image.py
pifcap/pifcap_ui.py
pifcap/settings.py
pifcap/settings_ui.py
pifcap-1.0.6.dist-info/LICENSE
pifcap-1.0.6.dist-info/METADATA
pifcap-1.0.6.dist-info/WHEEL
pifcap-1.0.6.dist-info/entry_points.txt
pifcap-1.0.6.dist-info/top_level.txt
pifcap-1.0.6.dist-info/RECORD
