Metadata-Version: 2.1
Name: pifcap
Version: 1.0.6
Summary: A GUI for fast RAW image capture on Raspberry Pi
Home-page: https://github.com/scriptorron/pifcap
Author: Ronald Schreiber
Author-email: ronald.schreiber01@gmx.de
Requires-Python: >=3.7
License-File: LICENSE
